sas/__init__.py
sas/handlers.py
sas/lexer.py
sas/parsebase.py
sas/ddl/__init__.py
sas/ddl/parser.py
sas/mmcif/__init__.py
sas/mmcif/parser.py
sas/nmrstar/__init__.py
sas/nmrstar/nvparser.py
sas/nmrstar/sansparser.py
sas/nmrstar/sasparser.py
bmrb_sas-1.0.0.dist-info/METADATA
bmrb_sas-1.0.0.dist-info/WHEEL
bmrb_sas-1.0.0.dist-info/top_level.txt
bmrb_sas-1.0.0.dist-info/RECORD
