Metadata-Version: 2.4
Name: bmrb-sas
Version: 1.0.0
Summary: Simple API for STAR (Self-describing Text Archive and Retrieval) format
Author-email: BMRB <help@bmrb.io>
License-Expression: MIT
Project-URL: Homepage, https://github.com/bmrb-io/sas
Project-URL: Repository, https://github.com/bmrb-io/sas
Project-URL: Documentation, https://github.com/bmrb-io/sas
Keywords: STAR,NMR-STAR,mmCIF,CIF,parser,BMRB
Classifier: Development Status :: 5 - Production/Stable
Classifier: Intended Audience :: Science/Research
Classifier: Operating System :: OS Independent
Classifier: Programming Language :: Python :: 3
Classifier: Programming Language :: Python :: 3.8
Classifier: Programming Language :: Python :: 3.9
Classifier: Programming Language :: Python :: 3.10
Classifier: Programming Language :: Python :: 3.11
Classifier: Programming Language :: Python :: 3.12
Classifier: Programming Language :: Python :: 3.13
Classifier: Topic :: Scientific/Engineering :: Bio-Informatics
Classifier: Topic :: Scientific/Engineering :: Chemistry
Requires-Python: >=3.8
Requires-Dist: ply<3.12,>3.10
